CHANGELOG.rst
MANIFEST.in
README.rst
setup.py
django_mailup.egg-info/PKG-INFO
django_mailup.egg-info/SOURCES.txt
django_mailup.egg-info/dependency_links.txt
django_mailup.egg-info/requires.txt
django_mailup.egg-info/top_level.txt
mailup/__init__.py
mailup/models.py
mailup/settings.py
mailup/tests.py
mailup/utils.py
mailup/views.py
mailup/webservice.py