Metadata-Version: 1.0
Name: django-mailup
Version: 0.1.1
Summary: A plugin to integrate Django and Mailup
Home-page: https://bitbucket.org/marcominutoli/django-mailup.git
Author: Marco Minutoli
Author-email: info@marcominutoli.it
License: BSD
Keywords: Newsletter,Django,Mailup
Platform: UNKNOWN
Classifier: Environment :: Web Environment
Classifier: Framework :: Django
Classifier: Intended Audience :: Developers
Classifier: License :: OSI Approved :: BSD License
Classifier: Operating System :: Unix
Classifier: Programming Language :: Python
